reimage/__init__.py
reimage/__main__.py
reimage/file_utils.py
reimage/utils.py
reimage-1.0.0.dist-info/LICENSE
reimage-1.0.0.dist-info/METADATA
reimage-1.0.0.dist-info/WHEEL
reimage-1.0.0.dist-info/entry_points.txt
reimage-1.0.0.dist-info/top_level.txt
reimage-1.0.0.dist-info/RECORD
