Metadata-Version: 2.1
Name: reimage
Version: 1.0.0
Summary: Image sorting utility based on creation time
Author: Vasil Vasilev
Author-email: vaskovasilev94@yahoo.com
License: UNKNOWN
Platform: UNKNOWN
Requires-Python: >=3.4
License-File: LICENSE
Requires-Dist: ffcount (>=0.1.9)
